.gitignore
CONTRIBUTING.md
LICENSE
Makefile
README.md
settings.ini
setup.py
.github/workflows/main.yml
docs/.gitignore
docs/Gemfile
docs/Gemfile.lock
docs/_config.yml
docs/feed.xml
docs/sidebar.json
docs/sitemap.xml
docs/tooltips.json
docs/_data/alerts.yml
docs/_data/definitions.yml
docs/_data/glossary.yml
docs/_data/tags.yml
docs/_data/terms.yml
docs/_data/topnav.yml
docs/_data/sidebars/home_sidebar.yml
docs/_includes/archive.html
docs/_includes/callout.html
docs/_includes/footer.html
docs/_includes/google_analytics.html
docs/_includes/head.html
docs/_includes/head_print.html
docs/_includes/image.html
docs/_includes/important.html
docs/_includes/initialize_shuffle.html
docs/_includes/inline_image.html
docs/_includes/links.html
docs/_includes/note.html
docs/_includes/search_google_custom.html
docs/_includes/search_simple_jekyll.html
docs/_includes/sidebar.html
docs/_includes/tip.html
docs/_includes/toc.html
docs/_includes/topnav.html
docs/_includes/warning.html
docs/_layouts/default.html
docs/_layouts/default_print.html
docs/_layouts/none.html
docs/_layouts/page.html
docs/_layouts/page_print.html
docs/css/bootstrap.min.css
docs/css/boxshadowproperties.css
docs/css/customstyles.css
docs/css/font-awesome.min.css
docs/css/modern-business.css
docs/css/printstyles.css
docs/css/syntax.css
docs/css/theme-blue.css
docs/css/theme-green.css
docs/css/fonts/FontAwesome.otf
docs/css/fonts/fontawesome-webfont.eot
docs/css/fonts/fontawesome-webfont.svg
docs/css/fonts/fontawesome-webfont.ttf
docs/css/fonts/fontawesome-webfont.woff
docs/css/fonts/fontawesome-webfont.woff2
docs/fonts/FontAwesome.otf
docs/fonts/fontawesome-webfont.eot
docs/fonts/fontawesome-webfont.svg
docs/fonts/fontawesome-webfont.ttf
docs/fonts/fontawesome-webfont.woff
docs/fonts/glyphicons-halflings-regular.eot
docs/fonts/glyphicons-halflings-regular.svg
docs/fonts/glyphicons-halflings-regular.ttf
docs/fonts/glyphicons-halflings-regular.woff
docs/fonts/glyphicons-halflings-regular.woff2
spellotape.egg-info/PKG-INFO
spellotape.egg-info/SOURCES.txt
spellotape.egg-info/dependency_links.txt
spellotape.egg-info/entry_points.txt
spellotape.egg-info/not-zip-safe
spellotape.egg-info/requires.txt
spellotape.egg-info/top_level.txt