Metadata-Version: 2.1
Name: spellotape
Version: 0.0.7
Summary: Miscellaneous utility functions for data science projects at GoGuardian.
Home-page: https://github.com/hdmamin/spellotape
Author: Harrison Mamin
Author-email: hmamin@goguardian.com
License: Apache Software License 2.0
Keywords: data science
Platform: UNKNOWN
Classifier: Development Status :: 3 - Alpha
Classifier: Intended Audience :: Developers
Classifier: License :: OSI Approved :: Apache Software License
Classifier: Natural Language :: English
Classifier: Programming Language :: Python :: 3.6
Classifier: Programming Language :: Python :: 3.7
Classifier: Programming Language :: Python :: 3.8
Requires-Python: >=3.6
